githubapp/__init__.py
githubapp/core.py
githubapp/oauth.py
githubapp/session.py
fastapi_githubapp-0.2.5.dist-info/LICENSE
fastapi_githubapp-0.2.5.dist-info/METADATA
fastapi_githubapp-0.2.5.dist-info/WHEEL
fastapi_githubapp-0.2.5.dist-info/RECORD
