Metadata-Version: 2.3
Name: fastapi-githubapp
Version: 0.2.5
Summary: FastAPI extension for rapid GitHub App development
License: MIT
Keywords: fastapi,github,app,oauth2,oauth,probot,githubapp,github-app
Author: primetheus
Author-email: 865381+primetheus@users.noreply.github.com
Requires-Python: >=3.9,<4.0
Classifier: Framework :: FastAPI
Classifier: License :: OSI Approved :: MIT License
Classifier: Operating System :: OS Independent
Classifier: Programming Language :: Python :: 3
Classifier: Programming Language :: Python :: 3.9
Classifier: Programming Language :: Python :: 3.10
Classifier: Programming Language :: Python :: 3.11
Classifier: Programming Language :: Python :: 3.12
Classifier: Programming Language :: Python :: 3.13
Requires-Dist: fastapi (>=0.95.0)
Requires-Dist: ghapi (>=1.0.0)
Requires-Dist: httpx (>=0.28.1)
Requires-Dist: pyjwt[crypto] (>=2.8.0)
Requires-Dist: uvicorn[standard] (>=0.22.0)
Project-URL: Homepage, https://github.com/primetheus/fastapi-githubapp
Project-URL: Repository, https://github.com/primetheus/fastapi-githubapp
